nescience/__init__.py
nescience/anomalies.py
nescience/classifier.py
nescience/inaccuracy.py
nescience/miscoding.py
nescience/nescience.py
nescience/regressor.py
nescience/surfeit.py
nescience/test_fastautoml.py
nescience/test_inaccuracy.py
nescience/test_miscoding.py
nescience/timeseries.py
nescience/utils.py
nescience-1.0.dist-info/METADATA
nescience-1.0.dist-info/WHEEL
nescience-1.0.dist-info/top_level.txt
nescience-1.0.dist-info/RECORD
