Metadata-Version: 2.1
Name: nescience
Version: 1.0
Summary: Machine Learning with the Minimum Nescience Principle
Home-page: https://github.com/rleiva/nescience
Author: R. Garcia Leiva
Author-email: rgarcialeiva@gmail.com
License: UNKNOWN
Platform: UNKNOWN
Classifier: Programming Language :: Python :: 3
Classifier: License :: OSI Approved :: GNU General Public License v3 (GPLv3)
Classifier: Operating System :: OS Independent
